samplePackage/__init__.py
samplePackage/python_code.py
jgpackage-0.0.2.dist-info/LICENSE
jgpackage-0.0.2.dist-info/METADATA
jgpackage-0.0.2.dist-info/WHEEL
jgpackage-0.0.2.dist-info/top_level.txt
jgpackage-0.0.2.dist-info/RECORD
