Metadata-Version: 2.1
Name: jgpackage
Version: 0.0.2
Summary: A beautiful sample package.
Home-page: UNKNOWN
Author: Juliana Guamá
Author-email: e@mail.com
Maintainer: juguama
Maintainer-email: e@mail.com
License: MIT
Keywords: bh,pyladies,tutorial
Platform: UNKNOWN
Classifier: Programming Language :: Python :: 3.7
Classifier: Operating System :: OS Independent
Classifier: License :: OSI Approved :: MIT License
Requires-Python: >=3.7
